genhtml/__init__.py
genhtml-2.0.0.dist-info/METADATA
genhtml-2.0.0.dist-info/WHEEL
genhtml-2.0.0.dist-info/top_level.txt
genhtml-2.0.0.dist-info/RECORD
