Metadata-Version: 2.1
Name: genhtml
Version: 2.0.0
Summary: Html5 generator
Home-page: UNKNOWN
Author: Vadim Simakin
Author-email: sima.vad@gmail.com
License: UNKNOWN
Platform: UNKNOWN
Classifier: Programming Language :: Python :: 3
Classifier: Operating System :: OS Independent
Requires-Python: >=3.7
Requires-Dist: bs4
Requires-Dist: lxml
